lms_filter_stage.v
// LMS Adaptive Filter Stage
module lms_filter_stage #(
    parameter FILTER_ORDER = 16,
    parameter DATA_WIDTH   = 16,
    parameter STEP_SIZE    = 16'h0100   // μ = 1/256
)(
    input  wire                  clk,
    input  wire                  rst_n,
    input  wire signed [DATA_WIDTH-1:0] audio_in,
    input  wire                  audio_valid,
    output reg signed [DATA_WIDTH-1:0] audio_out,
    output reg                   audio_ready
);
    reg signed [DATA_WIDTH-1:0] weights [0:FILTER_ORDER-1];
    reg signed [DATA_WIDTH-1:0] delay_line [0:FILTER_ORDER-1];
    reg signed [DATA_WIDTH-1:0] desired_signal;
    reg signed [2*DATA_WIDTH-1:0] filter_output_acc;
    reg signed [DATA_WIDTH-1:0] filter_output, error_signal;
    integer i;

    always @(posedge clk or negedge rst_n) begin
        if (!rst_n) begin
            for (i = 0; i < FILTER_ORDER; i=i+1) begin
                weights[i] <= 0;
                delay_line[i] <= 0;
            end
            filter_output <= 0;
            audio_out <= 0;
            audio_ready <= 0;
        end else if (audio_valid) begin
            // Shift delay line
            for (i = FILTER_ORDER-1; i > 0; i=i-1) begin
                delay_line[i] <= delay_line[i-1];
            end
            delay_line[0] <= audio_in;

            // Compute filter output (MAC)
            filter_output_acc = 0;
            for (i = 0; i < FILTER_ORDER; i=i+1) begin
                filter_output_acc = filter_output_acc + weights[i] * delay_line[i];
            end
            filter_output <= filter_output_acc[2*DATA_WIDTH-2:DATA_WIDTH-1];

            // Desired signal: delayed version
            desired_signal <= delay_line[FILTER_ORDER/2];

            // Error calculation
            error_signal <= desired_signal - filter_output;

            // Update weights (LMS)
            for (i = 0; i < FILTER_ORDER; i=i+1) begin
                weights[i] <= weights[i] + ((STEP_SIZE * error_signal * delay_line[i]) >>> 16);
            end

            // Output
            audio_out <= filter_output;
            audio_ready <= 1;
        end else begin
            audio_ready <= 0;
        end
    end
endmodule

spectral_subtraction_stage.v
// Simplified Spectral Subtraction Stage
module spectral_subtraction_stage(
    input  wire         clk,
    input  wire         rst_n,
    input  wire signed [15:0] audio_in,
    input  wire         audio_valid,
    output reg signed [15:0] audio_out,
    output reg          audio_ready
);
    parameter integer NOISE_LEN = 256; // Number of samples for noise estimate
    reg [31:0] noise_sum;
    reg [15:0] noise_est;
    reg [7:0]  count;
    reg        noise_ready;

    wire [15:0] abs_sample = (audio_in[15] ? -audio_in : audio_in);

    always @(posedge clk or negedge rst_n) begin
        if (!rst_n) begin
            noise_sum   <= 0;
            count       <= 0;
            noise_est   <= 0;
            noise_ready <= 0;
            audio_out   <= 0;
            audio_ready <= 0;
        end else if (audio_valid) begin
            if (!noise_ready) begin
                // Accumulate noise estimate
                noise_sum <= noise_sum + abs_sample;
                count <= count + 1;
                if (count == NOISE_LEN-1) begin
                    noise_est   <= noise_sum >> 8; // divide by 256
                    noise_ready <= 1;
                end
                audio_ready <= 0;
            end else begin
                // Subtract noise estimate
                if (audio_in >= 0) begin
                    if (audio_in > noise_est)
                        audio_out <= audio_in - noise_est;
                    else
                        audio_out <= 0;
                end else begin
                    if (audio_in < -noise_est)
                        audio_out <= audio_in + noise_est;
                    else
                        audio_out <= 0;
                end
                audio_ready <= 1;
            end
        end else begin
            audio_ready <= 0;
        end
    end
endmodule

hearing_aid_processor.v
// Top-level dual-stage hearing aid noise removal processor
module hearing_aid_processor(
    input  wire         clk,
    input  wire         rst_n,
    input  wire signed [15:0] audio_in,
    input  wire         audio_valid,
    output wire signed [15:0] audio_out,
    output wire         audio_ready
);
    // Internal connections
    wire signed [15:0] stage1_out, stage2_out;
    wire stage1_ready, stage2_ready;

    // Stage 1: Spectral subtraction
    spectral_subtraction_stage stage1 (
        .clk(clk), .rst_n(rst_n),
        .audio_in(audio_in),
        .audio_valid(audio_valid),
        .audio_out(stage1_out),
        .audio_ready(stage1_ready)
    );

    // Stage 2: LMS adaptive filter
    lms_filter_stage stage2 (
        .clk(clk), .rst_n(rst_n),
        .audio_in(stage1_out),
        .audio_valid(stage1_ready),
        .audio_out(stage2_out),
        .audio_ready(stage2_ready)
    );

    // Output assignment
    assign audio_out   = stage2_out;
    assign audio_ready = stage2_ready;
endmodule

hearing_aid_testbench.v
// Testbench for the hearing aid processor
module hearing_aid_testbench;
    reg         clk, rst_n;
    reg signed [15:0] audio_in;
    reg         audio_valid;
    wire signed [15:0] audio_out;
    wire        audio_ready;
    real        phase;

    // Instantiate DUT
    hearing_aid_processor dut (
        .clk(clk), .rst_n(rst_n),
        .audio_in(audio_in), .audio_valid(audio_valid),
        .audio_out(audio_out), .audio_ready(audio_ready)
    );

    // Clock generation (100 MHz)
    initial clk = 0;
    always #5 clk = ~clk;

    // Stimulus
    initial begin
        $dumpfile("hearing_aid.vcd");          // Name of VCD file to create
        $dumpvars(0, hearing_aid_testbench);   // Dump all signals in the testbench
        rst_n = 0;
        audio_valid = 0;
        audio_in = 0;
        phase = 0.0;
        #100; // Reset duration
        rst_n = 1;

        repeat (1000) begin
            @(posedge clk);
            // Sine wave + noise
            phase = phase + 0.05;
            audio_in    <= $rtoi(1000.0 * $sin(phase)) + ($random % 512);
            audio_valid <= 1;
            @(posedge clk);
            audio_valid <= 0;
            repeat (4) @(posedge clk);
        end

        $finish;
    end

    // Output monitor
    always @(posedge clk) begin
        if (audio_ready) begin
            $display("Time %0t: Input=%d, Output=%d",
                     $time, audio_in, audio_out);
        end
    end
endmodule

hearing_aid.vcd
$date
	Wed Sep 10 01:03:40 2025
$end
$version
	Icarus Verilog
$end
$timescale
	1s
$end
$scope module hearing_aid_testbench $end
$var wire 1 ! audio_ready $end
$var wire 16 " audio_out [15:0] $end
$var reg 16 # audio_in [15:0] $end
$var reg 1 $ audio_valid $end
$var reg 1 % clk $end
$var reg 1 & rst_n $end
$var real 1 ' phase $end
$scope module dut $end
$var wire 16 ( audio_in [15:0] $end
$var wire 16 ) audio_out [15:0] $end
$var wire 1 ! audio_ready $end
$var wire 1 $ audio_valid $end
$var wire 1 % clk $end
$var wire 1 & rst_n $end
$var wire 1 * stage2_ready $end
$var wire 16 + stage2_out [15:0] $end
$var wire 1 , stage1_ready $end
$var wire 16 - stage1_out [15:0] $end
$scope module stage1 $end
$var wire 16 . audio_in [15:0] $end
$var wire 1 $ audio_valid $end
$var wire 1 % clk $end
$var wire 1 & rst_n $end
$var wire 16 / abs_sample [15:0] $end
$var parameter 32 0 NOISE_LEN $end
$var reg 16 1 audio_out [15:0] $end
$var reg 1 , audio_ready $end
$var reg 8 2 count [7:0] $end
$var reg 16 3 noise_est [15:0] $end
$var reg 1 4 noise_ready $end
$var reg 32 5 noise_sum [31:0] $end
$upscope $end
$scope module stage2 $end
$var wire 16 6 audio_in [15:0] $end
$var wire 1 , audio_valid $end
$var wire 1 % clk $end
$var wire 1 & rst_n $end
$var parameter 32 7 DATA_WIDTH $end
$var parameter 32 8 FILTER_ORDER $end
$var parameter 16 9 STEP_SIZE $end
$var reg 16 : audio_out [15:0] $end
$var reg 1 * audio_ready $end
$var reg 16 ; desired_signal [15:0] $end
$var reg 16 < error_signal [15:0] $end
$var reg 16 = filter_output [15:0] $end
$var reg 32 > filter_output_acc [31:0] $end
$var integer 32 ? i [31:0] $end
$upscope $end
$upscope $end
$upscope $end
$enddefinitions $end
$comment Show the parameter values. $end
$dumpall
b100000000 9
b10000 8
b10000 7
b100000000 0
$end
#0
$dumpvars
b10000 ?
bx >
b0 =
bx <
bx ;
b0 :
b0 6
b0 5
04
b0 3
b0 2
b0 1
b0 /
b0 .
b0 -
0,
b0 +
0*
b0 )
b0 (
r0 '
0&
0%
0$
b0 #
b0 "
0!
$end
#5
b10000 ?
1%
#10
0%
#15
b10000 ?
1%
#20
0%
#25
b10000 ?
1%
#30
0%
#35
b10000 ?
1%
#40
0%
#45
b10000 ?
1%
#50
0%
#55
b10000 ?
1%
#60
0%
#65
b10000 ?
1%
#70
0%
#75
b10000 ?
1%
#80
0%
#85
b10000 ?
1%
#90
0%
#95
b10000 ?
1%
#100
0%
1&
#105
b101010101 /
1$
b101010101 #
b101010101 (
b101010101 .
r0.05 '
1%
#110
0%
#115
b1 2
b101010101 5
0$
1%
#120
0%
#125
1%
#130
0%
#135
1%
#140
0%
#145
1%
#150
0%
#155
1%
#160
0%
#165
b100011100 /
1$
b1111111011100100 #
b1111111011100100 (
b1111111011100100 .
r0.1 '
1%
#170
0%
#175
b10 2
b1001110001 5
0$
1%
#180
0%
#185
1%
#190
0%
#195
1%
#200
0%
#205
1%
#210
0%
#215
1%
#220
0%
#225
b101100010 /
1$
b1111111010011110 #
b1111111010011110 (
b1111111010011110 .
r0.15 '
1%
#230
0%
#235
b11 2
b1111010011 5
0$
1%
#240
0%
#245
1%
#250
0%
#255
1%
#260
0%
#265
1%
#270
0%
#275
1%
#280
0%
#285
b11010111 /
1$
b1111111100101001 #
b1111111100101001 (
b1111111100101001 .
r0.2 '
1%
#290
0%
#295
b100 2
b10010101010 5
0$
1%
#300
0%
#305
1%
#310
0%
#315
1%
#320
0%
#325
1%
#330
0%
#335
1%
#340
0%
#345
b1000000100 /
1$
b1000000100 #
b1000000100 (
b1000000100 .
r0.25 '
1%
#350
0%
#355
b101 2
b11010101110 5
0$
1%
#360
0%
#365
1%
#370
0%
#375
1%
#380
0%
#385
1%
#390
0%
#395
1%
#400
0%
#405
b1010110100 /
1$
b1010110100 #
b1010110100 (
b1010110100 .
r0.3 '
1%
#410
0%
#415
b110 2
b100101100010 5
0$
1%
#420
0%
#425
1%
#430
0%
#435
1%
#440
0%
#445
1%
#450
0%
#455
1%
#460
0%
#465
b1000101 /
1$
b1111111110111011 #
b1111111110111011 (
b1111111110111011 .
r0.35 '
1%
#470
0%
#475
b111 2
b100110100111 5
0$
1%
#480
0%
#485
1%
#490
0%
#495
1%
#500
0%
#505
1%
#510
0%
#515
1%
#520
0%
#525
b1101001 /
1$
b1111111110010111 #
b1111111110010111 (
b1111111110010111 .
r0.4 '
1%
#530
0%
#535
b1000 2
b101000010000 5
0$
1%
#540
0%
#545
1%
#550
0%
#555
1%
#560
0%
#565
1%
#570
0%
#575
1%
#580
0%
#585
b1010110011 /
1$
b1010110011 #
b1010110011 (
b1010110011 .
r0.45 '
1%
#590
0%
#595
b1001 2
b110011000011 5
0$
1%
#600
0%
#605
1%
#610
0%
#615
1%
#620
0%
#625
1%
#630
0%
#635
1%
#640
0%
#645
b1011101100 /
1$
b1011101100 #
b1011101100 (
b1011101100 .
r0.4999999999999999 '
1%
#650
0%
#655
b1010 2
b111110101111 5
0$
1%
#660
0%
#665
1%
#670
0%
#675
1%
#680
0%
#685
1%
#690
0%
#695
1%
#700
0%
#705
b1110000000 /
1$
b1110000000 #
b1110000000 (
b1110000000 .
r0.5499999999999999 '
1%
#710
0%
#715
b1011 2
b1001100101111 5
0$
1%
#720
0%
#725
1%
#730
0%
#735
1%
#740
0%
#745
1%
#750
0%
#755
1%
#760
0%
#765
b1101110001 /
1$
b1101110001 #
b1101110001 (
b1101110001 .
r0.6 '
1%
#770
0%
#775
b1100 2
b1011010100000 5
0$
1%
#780
0%
#785
1%
#790
0%
#795
1%
#800
0%
#805
1%
#810
0%
#815
1%
#820
0%
#825
b10001001010 /
1$
b10001001010 #
b10001001010 (
b10001001010 .
r0.65 '
1%
#830
0%
#835
b1101 2
b1101011101010 5
0$
1%
#840
0%
#845
1%
#850
0%
#855
1%
#860
0%
#865
1%
#870
0%
#875
1%
#880
0%
#885
b10000010000 /
1$
b10000010000 #
b10000010000 (
b10000010000 .
r0.7000000000000001 '
1%
#890
0%
#895
b1110 2
b1111011111010 5
0$
1%
#900
0%
#905
1%
#910
0%
#915
1%
#920
0%
#925
1%
#930
0%
#935
1%
#940
0%
#945
b10010100010 /
1$
b10010100010 #
b10010100010 (
b10010100010 .
r0.7500000000000001 '
1%
#950
0%
#955
b1111 2
b10001110011100 5
0$
1%
#960
0%
#965
1%
#970
0%
#975
1%
#980
0%
#985
1%
#990
0%
#995
1%
#1000
0%
#1005
b110010011 /
1$
b110010011 #
b110010011 (
b110010011 .
r0.8000000000000002 '
1%
#1010
0%
#1015
b10000 2
b10010100101111 5
0$
1%
#1020
0%
#1025
1%
#1030
0%
#1035
1%
#1040
0%
#1045
1%
#1050
0%
#1055
1%
#1060
0%
#1065
b110110100 /
1$
b110110100 #
b110110100 (
b110110100 .
r0.8500000000000002 '
1%
#1070
0%
#1075
b10001 2
b10011011100011 5
0$
1%
#1080
0%
#1085
1%
#1090
0%
#1095
1%
#1100
0%
#1105
1%
#1110
0%
#1115
1%
#1120
0%
#1125
b110111001 /
1$
b110111001 #
b110111001 (
b110111001 .
r0.9000000000000002 '
1%
#1130
0%
#1135
b10010 2
b10100010011100 5
0$
1%
#1140
0%
#1145
1%
#1150
0%
#1155
1%
#1160
0%
#1165
1%
#1170
0%
#1175
1%
#1180
0%
#1185
b10100010010 /
1$
b10100010010 #
b10100010010 (
b10100010010 .
r0.9500000000000003 '
1%
#1190
0%
#1195
b10011 2
b10110110101110 5
0$
1%
#1200
0%
#1205
1%
#1210
0%
#1215
1%
#1220
0%
#1225
1%
#1230
0%
#1235
1%
#1240
0%
#1245
b111000000 /
1$
b111000000 #
b111000000 (
b111000000 .
r1 '
1%
#1250
0%
#1255
b10100 2
b10111101101110 5
0$
1%
#1260
0%
#1265
1%
#1270
0%
#1275
1%
#1280
0%
#1285
1%
#1290
0%
#1295
1%
#1300
0%
#1305
b101110101 /
1$
b101110101 #
b101110101 (
b101110101 .
r1.05 '
1%
#1310
0%
#1315
b10101 2
b11000011100011 5
0$
1%
#1320
0%
#1325
1%
#1330
0%
#1335
1%
#1340
0%
#1345
1%
#1350
0%
#1355
1%
#1360
0%
#1365
b10100001010 /
1$
b10100001010 #
b10100001010 (
b10100001010 .
r1.1 '
1%
#1370
0%
#1375
b10110 2
b11010111101101 5
0$
1%
#1380
0%
#1385
1%
#1390
0%
#1395
1%
#1400
0%
#1405
1%
#1410
0%
#1415
1%
#1420
0%
#1425
b10110000010 /
1$
b10110000010 #
b10110000010 (
b10110000010 .
r1.15 '
1%
#1430
0%
#1435
b10111 2
b11101101101111 5
0$
1%
#1440
0%
#1445
1%
#1450
0%
#1455
1%
#1460
0%
#1465
1%
#1470
0%
#1475
1%
#1480
0%
#1485
b1001110010 /
1$
b1001110010 #
b1001110010 (
b1001110010 .
r1.2 '
1%
#1490
0%
#1495
b11000 2
b11110111100001 5
0$
1%
#1500
0%
#1505
1%
#1510
0%
#1515
1%
#1520
0%
#1525
1%
#1530
0%
#1535
1%
#1540
0%
#1545
b1010011100 /
1$
b1010011100 #
b1010011100 (
b1010011100 .
r1.25 '
1%
#1550
0%
#1555
b11001 2
b100000001111101 5
0$
1%
#1560
0%
#1565
1%
#1570
0%
#1575
1%
#1580
0%
#1585
1%
#1590
0%
#1595
1%
#1600
0%
#1605
b1010001000 /
1$
b1010001000 #
b1010001000 (
b1010001000 .
r1.3 '
1%
#1610
0%
#1615
b11010 2
b100001100000101 5
0$
1%
#1620
0%
#1625
1%
#1630
0%
#1635
1%
#1640
0%
#1645
1%
#1650
0%
#1655
1%
#1660
0%
#1665
b10100101011 /
1$
b10100101011 #
b10100101011 (
b10100101011 .
r1.350000000000001 '
1%
#1670
0%
#1675
b11011 2
b100100000110000 5
0$
1%
#1680
0%
#1685
1%
#1690
0%
#1695
1%
#1700
0%
#1705
1%
#1710
0%
#1715
1%
#1720
0%
#1725
b1010010110 /
1$
b1010010110 #
b1010010110 (
b1010010110 .
r1.400000000000001 '
1%
#1730
0%
#1735
b11100 2
b100101011000110 5
0$
1%
#1740
0%
#1745
1%
#1750
0%
#1755
1%
#1760
0%
#1765
1%
#1770
0%
#1775
1%
#1780
0%
#1785
b1000001101 /
1$
b1000001101 #
b1000001101 (
b1000001101 .
r1.450000000000001 '
1%
#1790
0%
#1795
b11101 2
b100110011010011 5
0$
1%
#1800
0%
#1805
1%
#1810
0%
#1815
1%
#1820
0%
#1825
1%
#1830
0%
#1835
1%
#1840
0%
#1845
b1001001010 /
1$
b1001001010 #
b1001001010 (
b1001001010 .
r1.500000000000001 '
1%
#1850
0%
#1855
b11110 2
b100111100011101 5
0$
1%
#1860
0%
#1865
1%
#1870
0%
#1875
1%
#1880
0%
#1885
1%
#1890
0%
#1895
1%
#1900
0%
#1905
1$
r1.550000000000001 '
1%
#1910
0%
#1915
b11111 2
b101000101100111 5
0$
1%
#1920
0%
#1925
1%
#1930
0%
#1935
1%
#1940
0%
#1945
1%
#1950
0%
#1955
1%
#1960
0%
#1965
b10011110001 /
1$
b10011110001 #
b10011110001 (
b10011110001 .
r1.600000000000001 '
1%
#1970
0%
#1975
b100000 2
b101011001011000 5
0$
1%
#1980
0%
#1985
1%
#1990
0%
#1995
1%
#2000
0%
#2005
1%
#2010
0%
#2015
1%
#2020
0%
#2025
b1001100100 /
1$
b1001100100 #
b1001100100 (
b1001100100 .
r1.650000000000001 '
1%
#2030
0%
#2035
b100001 2
b101100010111100 5
0$
1%
#2040
0%
#2045
1%
#2050
0%
#2055
1%
#2060
0%
#2065
1%
#2070
0%
#2075
1%
#2080
0%
#2085
b10011111111 /
1$
b10011111111 #
b10011111111 (
b10011111111 .
r1.700000000000001 '
1%
#2090
0%
#2095
b100010 2
b101110110111011 5
0$
1%
#2100
0%
#2105
1%
#2110
0%
#2115
1%
#2120
0%
#2125
1%
#2130
0%
#2135
1%
#2140
0%
#2145
b10110000001 /
1$
b10110000001 #
b10110000001 (
b10110000001 .
r1.750000000000001 '
1%
#2150
0%
#2155
b100011 2
b110001100111100 5
0$
1%
#2160
0%
#2165
1%
#2170
0%
#2175
1%
#2180
0%
#2185
1%
#2190
0%
#2195
1%
#2200
0%
#2205
b1001101010 /
1$
b1001101010 #
b1001101010 (
b1001101010 .
r1.800000000000001 '
1%
#2210
0%
#2215
b100100 2
b110010110100110 5
0$
1%
#2220
0%
#2225
1%
#2230
0%
#2235
1%
#2240
0%
#2245
1%
#2250
0%
#2255
1%
#2260
0%
#2265
b1001010111 /
1$
b1001010111 #
b1001010111 (
b1001010111 .
r1.850000000000001 '
1%
#2270
0%
#2275
b100101 2
b110011111111101 5
0$
1%
#2280
0%
#2285
1%
#2290
0%
#2295
1%
#2300
0%
#2305
1%
#2310
0%
#2315
1%
#2320
0%
#2325
b111000101 /
1$
b111000101 #
b111000101 (
b111000101 .
r1.900000000000001 '
1%
#2330
0%
#2335
b100110 2
b110100111000010 5
0$
1%
#2340
0%
#2345
1%
#2350
0%
#2355
1%
#2360
0%
#2365
1%
#2370
0%
#2375
1%
#2380
0%
#2385
b110101101 /
1$
b110101101 #
b110101101 (
b110101101 .
r1.950000000000001 '
1%
#2390
0%
#2395
b100111 2
b110101101101111 5
0$
1%
#2400
0%
#2405
1%
#2410
0%
#2415
1%
#2420
0%
#2425
1%
#2430
0%
#2435
1%
#2440
0%
#2445
b111100000 /
1$
b111100000 #
b111100000 (
b111100000 .
r2.000000000000001 '
1%
#2450
0%
#2455
b101000 2
b110110101001111 5
0$
1%
#2460
0%
#2465
1%
#2470
0%
#2475
1%
#2480
0%
#2485
1%
#2490
0%
#2495
1%
#2500
0%
#2505
b10011100010 /
1$
b10011100010 #
b10011100010 (
b10011100010 .
r2.050000000000001 '
1%
#2510
0%
#2515
b101001 2
b111001000110001 5
0$
1%
#2520
0%
#2525
1%
#2530
0%
#2535
1%
#2540
0%
#2545
1%
#2550
0%
#2555
1%
#2560
0%
#2565
b1000110100 /
1$
b1000110100 #
b1000110100 (
b1000110100 .
r2.100000000000001 '
1%
#2570
0%
#2575
b101010 2
b111010001100101 5
0$
1%
#2580
0%
#2585
1%
#2590
0%
#2595
1%
#2600
0%
#2605
1%
#2610
0%
#2615
1%
#2620
0%
#2625
b101000110 /
1$
b101000110 #
b101000110 (
b101000110 .
r2.15 '
1%
#2630
0%
#2635
b101011 2
b111010110101011 5
0$
1%
#2640
0%
#2645
1%
#2650
0%
#2655
1%
#2660
0%
#2665
1%
#2670
0%
#2675
1%
#2680
0%
#2685
b111010110 /
1$
b111010110 #
b111010110 (
b111010110 .
r2.2 '
1%
#2690
0%
#2695
b101100 2
b111011110000001 5
0$
1%
#2700
0%
#2705
1%
#2710
0%
#2715
1%
#2720
0%
#2725
1%
#2730
0%
#2735
1%
#2740
0%
#2745
b10000100111 /
1$
b10000100111 #
b10000100111 (
b10000100111 .
r2.25 '
1%
#2750
0%
#2755
b101101 2
b111101110101000 5
0$
1%
#2760
0%
#2765
1%
#2770
0%
#2775
1%
#2780
0%
#2785
1%
#2790
0%
#2795
1%
#2800
0%
#2805
b110111000 /
1$
b110111000 #
b110111000 (
b110111000 .
r2.3 '
1%
#2810
0%
#2815
b101110 2
b111110101100000 5
0$
1%
#2820
0%
#2825
1%
#2830
0%
#2835
1%
#2840
0%
#2845
1%
#2850
0%
#2855
1%
#2860
0%
#2865
b1111101010 /
1$
b1111101010 #
b1111101010 (
b1111101010 .
r2.35 '
1%
#2870
0%
#2875
b101111 2
b1000000101001010 5
0$
1%
#2880
0%
#2885
1%
#2890
0%
#2895
1%
#2900
0%
#2905
1%
#2910
0%
#2915
1%
#2920
0%
#2925
b1110101101 /
1$
b1110101101 #
b1110101101 (
b1110101101 .
r2.399999999999999 '
1%
#2930
0%
#2935
b110000 2
b1000010011110111 5
0$
1%
#2940
0%
#2945
1%
#2950
0%
#2955
1%
#2960
0%
#2965
1%
#2970
0%
#2975
1%
#2980
0%
#2985
b101000111 /
1$
b101000111 #
b101000111 (
b101000111 .
r2.449999999999999 '
1%
#2990
0%
#2995
b110001 2
b1000011000111110 5
0$
1%
#3000
0%
#3005
1%
#3010
0%
#3015
1%
#3020
0%
#3025
1%
#3030
0%
#3035
1%
#3040
0%
#3045
b10010010 /
1$
b10010010 #
b10010010 (
b10010010 .
r2.499999999999999 '
1%
#3050
0%
#3055
b110010 2
b1000011011010000 5
0$
1%
#3060
0%
#3065
1%
#3070
0%
#3075
1%
#3080
0%
#3085
1%
#3090
0%
#3095
1%
#3100
0%
#3105
b10000011111 /
1$
b10000011111 #
b10000011111 (
b10000011111 .
r2.549999999999999 '
1%
#3110
0%
#3115
b110011 2
b1000101011101111 5
0$
1%
#3120
0%
#3125
1%
#3130
0%
#3135
1%
#3140
0%
#3145
1%
#3150
0%
#3155
1%
#3160
0%
#3165
b1110001101 /
1$
b1110001101 #
b1110001101 (
b1110001101 .
r2.599999999999999 '
1%
#3170
0%
#3175
b110100 2
b1000111001111100 5
0$
1%
#3180
0%
#3185
1%
#3190
0%
#3195
1%
#3200
0%
#3205
1%
#3210
0%
#3215
1%
#3220
0%
#3225
b1100011001 /
1$
b1100011001 #
b1100011001 (
b1100011001 .
r2.649999999999999 '
1%
#3230
0%
#3235
b110101 2
b1001000110010101 5
0$
1%
#3240
0%
#3245
1%
#3250
0%
#3255
1%
#3260
0%
#3265
1%
#3270
0%
#3275
1%
#3280
0%
#3285
b10000011 /
1$
b10000011 #
b10000011 (
b10000011 .
r2.699999999999998 '
1%
#3290
0%
#3295
b110110 2
b1001001000011000 5
0$
1%
#3300
0%
#3305
1%
#3310
0%
#3315
1%
#3320
0%
#3325
1%
#3330
0%
#3335
1%
#3340
0%
#3345
b1011110101 /
1$
b1011110101 #
b1011110101 (
b1011110101 .
r2.749999999999998 '
1%
#3350
0%
#3355
b110111 2
b1001010100001101 5
0$
1%
#3360
0%
#3365
1%
#3370
0%
#3375
1%
#3380
0%
#3385
1%
#3390
0%
#3395
1%
#3400
0%
#3405
b101001 /
1$
b1111111111010111 #
b1111111111010111 (
b1111111111010111 .
r2.799999999999998 '
1%
#3410
0%
#3415
b111000 2
b1001010100110110 5
0$
1%
#3420
0%
#3425
1%
#3430
0%
#3435
1%
#3440
0%
#3445
1%
#3450
0%
#3455
1%
#3460
0%
#3465
b1100001010 /
1$
b1100001010 #
b1100001010 (
b1100001010 .
r2.849999999999998 '
1%
#3470
0%
#3475
b111001 2
b1001100001000000 5
0$
1%
#3480
0%
#3485
1%
#3490
0%
#3495
1%
#3500
0%
#3505
1%
#3510
0%
#3515
1%
#3520
0%
#3525
b1010100101 /
1$
b1010100101 #
b1010100101 (
b1010100101 .
r2.899999999999998 '
1%
#3530
0%
#3535
b111010 2
b1001101011100101 5
0$
1%
#3540
0%
#3545
1%
#3550
0%
#3555
1%
#3560
0%
#3565
1%
#3570
0%
#3575
1%
#3580
0%
#3585
b1010000100 /
1$
b1010000100 #
b1010000100 (
b1010000100 .
r2.949999999999998 '
1%
#3590
0%
#3595
b111011 2
b1001110101101001 5
0$
1%
#3600
0%
#3605
1%
#3610
0%
#3615
1%
#3620
0%
#3625
1%
#3630
0%
#3635
1%
#3640
0%
#3645
b1000111011 /
1$
b1000111011 #
b1000111011 (
b1000111011 .
r2.999999999999997 '
1%
#3650
0%
#3655
b111100 2
b1001111110100100 5
0$
1%
#3660
0%
#3665
1%
#3670
0%
#3675
1%
#3680
0%
#3685
1%
#3690
0%
#3695
1%
#3700
0%
#3705
b11101001 /
1$
b1111111100010111 #
b1111111100010111 (
b1111111100010111 .
r3.049999999999997 '
1%
#3710
0%
#3715
b111101 2
b1010000010001101 5
0$
1%
#3720
0%
#3725
1%
#3730
0%
#3735
1%
#3740
0%
#3745
1%
#3750
0%
#3755
1%
#3760
0%
#3765
b101010011 /
1$
b101010011 #
b101010011 (
b101010011 .
r3.099999999999997 '
1%
#3770
0%
#3775
b111110 2
b1010000111100000 5
0$
1%
#3780
0%
#3785
1%
#3790
0%
#3795
1%
#3800
0%
#3805
1%
#3810
0%
#3815
1%
#3820
0%
#3825
b111111101 /
1$
b1111111000000011 #
b1111111000000011 (
b1111111000000011 .
r3.149999999999997 '
1%
#3830
0%
#3835
b111111 2
b1010001111011101 5
0$
1%
#3840
0%
#3845
1%
#3850
0%
#3855
1%
#3860
0%
#3865
1%
#3870
0%
#3875
1%
#3880
0%
#3885
b111001001 /
1$
b1111111000110111 #
b1111111000110111 (
b1111111000110111 .
r3.199999999999997 '
1%
#3890
0%
#3895
b1000000 2
b1010010110100110 5
0$
1%
#3900
0%
#3905
1%
#3910
0%
#3915
1%
#3920
0%
#3925
1%
#3930
0%
#3935
1%
#3940
0%
#3945
b100011001 /
1$
b100011001 #
b100011001 (
b100011001 .
r3.249999999999996 '
1%
#3950
0%
#3955
b1000001 2
b1010011010111111 5
0$
1%
#3960
0%
#3965
1%
#3970
0%
#3975
1%
#3980
0%
#3985
1%
#3990
0%
#3995
1%
#4000
0%
#4005
b10110010 /
1$
b10110010 #
b10110010 (
b10110010 .
r3.299999999999996 '
1%
#4010
0%
#4015
b1000010 2
b1010011101110001 5
0$
1%
#4020
0%
#4025
1%
#4030
0%
#4035
1%
#4040
0%
#4045
1%
#4050
0%
#4055
1%
#4060
0%
#4065
b1010010011 /
1$
b1111110101101101 #
b1111110101101101 (
b1111110101101101 .
r3.349999999999996 '
1%
#4070
0%
#4075
b1000011 2
b1010101000000100 5
0$
1%
#4080
0%
#4085
1%
#4090
0%
#4095
1%
#4100
0%
#4105
1%
#4110
0%
#4115
1%
#4120
0%
#4125
b111011 /
1$
b111011 #
b111011 (
b111011 .
r3.399999999999996 '
1%
#4130
0%
#4135
b1000100 2
b1010101000111111 5
0$
1%
#4140
0%
#4145
1%
#4150
0%
#4155
1%
#4160
0%
#4165
1%
#4170
0%
#4175
1%
#4180
0%
#4185
b1010110001 /
1$
b1111110101001111 #
b1111110101001111 (
b1111110101001111 .
r3.449999999999996 '
1%
#4190
0%
#4195
b1000101 2
b1010110011110000 5
0$
1%
#4200
0%
#4205
1%
#4210
0%
#4215
1%
#4220
0%
#4225
1%
#4230
0%
#4235
1%
#4240
0%
#4245
b1001001 /
1$
b1111111110110111 #
b1111111110110111 (
b1111111110110111 .
r3.499999999999996 '
1%
#4250
0%
#4255
b1000110 2
b1010110100111001 5
0$
1%
#4260
0%
#4265
1%
#4270
0%
#4275
1%
#4280
0%
#4285
1%
#4290
0%
#4295
1%
#4300
0%
#4305
b1100100 /
1$
b1100100 #
b1100100 (
b1100100 .
r3.549999999999995 '
1%
#4310
0%
#4315
b1000111 2
b1010110110011101 5
0$
1%
#4320
0%
#4325
1%
#4330
0%
#4335
1%
#4340
0%
#4345
1%
#4350
0%
#4355
1%
#4360
0%
#4365
b11111 /
1$
b11111 #
b11111 (
b11111 .
r3.599999999999995 '
1%
#4370
0%
#4375
b1001000 2
b1010110110111100 5
0$
1%
#4380
0%
#4385
1%
#4390
0%
#4395
1%
#4400
0%
#4405
1%
#4410
0%
#4415
1%
#4420
0%
#4425
b10000100 /
1$
b1111111101111100 #
b1111111101111100 (
b1111111101111100 .
r3.649999999999995 '
1%
#4430
0%
#4435
b1001001 2
b1010111001000000 5
0$
1%
#4440
0%
#4445
1%
#4450
0%
#4455
1%
#4460
0%
#4465
1%
#4470
0%
#4475
1%
#4480
0%
#4485
b11000101 /
1$
b1111111100111011 #
b1111111100111011 (
b1111111100111011 .
r3.699999999999995 '
1%
#4490
0%
#4495
b1001010 2
b1010111100000101 5
0$
1%
#4500
0%
#4505
1%
#4510
0%
#4515
1%
#4520
0%
#4525
1%
#4530
0%
#4535
1%
#4540
0%
#4545
b10011100 /
1$
b1111111101100100 #
b1111111101100100 (
b1111111101100100 .
r3.749999999999995 '
1%
#4550
0%
#4555
b1001011 2
b1010111110100001 5
0$
1%
#4560
0%
#4565
1%
#4570
0%
#4575
1%
#4580
0%
#4585
1%
#4590
0%
#4595
1%
#4600
0%
#4605
b11010100 /
1$
b1111111100101100 #
b1111111100101100 (
b1111111100101100 .
r3.799999999999994 '
1%
#4610
0%
#4615
b1001100 2
b1011000001110101 5
0$
1%
#4620
0%
#4625
1%
#4630
0%
#4635
1%
#4640
0%
#4645
1%
#4650
0%
#4655
1%
#4660
0%
